zwift/__init__.py
zwift/activity.py
zwift/auth.py
zwift/client.py
zwift/error.py
zwift/profile.py
zwift/request.py
zwift/world.py
zwift/zwift_messages_pb2.py
zwift_client-0.2.0.dist-info/DESCRIPTION.rst
zwift_client-0.2.0.dist-info/METADATA
zwift_client-0.2.0.dist-info/RECORD
zwift_client-0.2.0.dist-info/WHEEL
zwift_client-0.2.0.dist-info/metadata.json
zwift_client-0.2.0.dist-info/top_level.txt
