Metadata-Version: 2.0
Name: zwift-client
Version: 0.2.0
Summary: Zwift Mobile API client.
Home-page: https://github.com/jsmits/zwift-client
Author: Sander Smits
Author-email: jhmsmits@gmail.com
License: MIT license
Keywords: zwift
Platform: UNKNOWN
Classifier: Development Status :: 2 - Pre-Alpha
Classifier: Intended Audience :: Developers
Classifier: License :: OSI Approved :: MIT License
Classifier: Natural Language :: English
Classifier: Programming Language :: Python :: 2
Classifier: Programming Language :: Python :: 2.7
Classifier: Programming Language :: Python :: 3
Classifier: Programming Language :: Python :: 3.4
Classifier: Programming Language :: Python :: 3.5
Classifier: Programming Language :: Python :: 3.6
Requires-Dist: fitparse
Requires-Dist: protobuf
Requires-Dist: requests
